hover_net/__init__.py
hover_net/config.py
hover_net/dataset.py
hover_net/run_infer.py
hover_net/run_train.py
hover_net/dataloader/__init__.py
hover_net/dataloader/augs.py
hover_net/dataloader/infer_loader.py
hover_net/dataloader/train_loader.py
hover_net/infer/__init__.py
hover_net/infer/base.py
hover_net/infer/tile.py
hover_net/infer/wsi.py
hover_net/metrics/__init__.py
hover_net/metrics/stats_utils.py
hover_net/misc/__init__.py
hover_net/misc/convert_format.py
hover_net/misc/patch_extractor.py
hover_net/misc/utils.py
hover_net/misc/viz_utils.py
hover_net/misc/wsi_handler.py
hover_net/models/__init__.py
hover_net/models/hovernet/__init__.py
hover_net/models/hovernet/net_desc.py
hover_net/models/hovernet/net_utils.py
hover_net/models/hovernet/opt.py
hover_net/models/hovernet/post_proc.py
hover_net/models/hovernet/run_desc.py
hover_net/models/hovernet/targets.py
hover_net/models/hovernet/utils.py
hover_net/run_utils/__init__.py
hover_net/run_utils/engine.py
hover_net/run_utils/utils.py
hover_net/run_utils/callbacks/__init__.py
hover_net/run_utils/callbacks/base.py
hover_net/run_utils/callbacks/logging.py
hover_net/run_utils/callbacks/serialize.py
hover_net/utils/__init__.py
hover_net/utils/compute_stats.py
hover_net/utils/convert_chkpt_tf2pytorch.py
hover_net/utils/extract_patches.py
tests/__init__.py
tests/test_hover_net.py
hover_net-0.0.10.dist-info/LICENSE
hover_net-0.0.10.dist-info/METADATA
hover_net-0.0.10.dist-info/WHEEL
hover_net-0.0.10.dist-info/entry_points.txt
hover_net-0.0.10.dist-info/top_level.txt
hover_net-0.0.10.dist-info/RECORD
