Metadata-Version: 2.1
Name: hover-net
Version: 0.0.10
Summary: HoVer-Net implementation fork
Home-page: https://github.com/leandermaerkisch/hover_net
Author: Leander Maerkisch
Author-email: l.maerkisch@gmail.com
Classifier: Programming Language :: Python :: 3
Classifier: License :: OSI Approved :: MIT License
Classifier: Operating System :: OS Independent
Requires-Python: >=3.6
License-File: LICENSE
Requires-Dist: future ==0.18.2
Requires-Dist: imgaug ==0.4.0
Requires-Dist: matplotlib <4.0.0,>=3.5.3
Requires-Dist: numpy <2.0.0,>=1.26.4
Requires-Dist: opencv-python <5.0.0,>=4.10.0.84
Requires-Dist: pandas <3.0.0,>=2.2.2
Requires-Dist: pillow <10.0.0,>=9.0.0
Requires-Dist: psutil <6.0.0,>=5.7.3
Requires-Dist: scikit-image <0.20.0,>=0.19.0
Requires-Dist: scikit-learn <2.0.0,>=1.0.0
Requires-Dist: torch <3.0.0,>=2.0.0
Requires-Dist: torchvision <1.0.0,>=0.15.0
Requires-Dist: tqdm <3.0.0,>=2.2.3
Requires-Dist: termcolor <3.0.0,>=2.4.0
Requires-Dist: openslide-python <2.0.0,>=1.3.1
